probe_utils.py
setup.py
probe/__init__.py
probe/utils/__init__.py
probe/utils/utils.py
probe_utils.egg-info/PKG-INFO
probe_utils.egg-info/SOURCES.txt
probe_utils.egg-info/dependency_links.txt
probe_utils.egg-info/entry_points.txt
probe_utils.egg-info/namespace_packages.txt
probe_utils.egg-info/pbr.json
probe_utils.egg-info/top_level.txt
probe_utils.egg-info/zip-safe