Metadata-Version: 1.0
Name: probe-utils
Version: 0.1.1
Summary: Utilities for probe simulations
Home-page: UNKNOWN
Author: Petr Zikan
Author-email: zikan.p@gmail.com
License: GPLv3
Platform: UNKNOWN
